{
  "id": "2860743961a41f1a6aac34bcbfc4ed70e79fab7f",
  "branch": "main",
  "classification": "dependency_update",
  "title": "some fixes",
  "summary": "",
  "commits": [
    "2860743961a41f1a6aac34bcbfc4ed70e79fab7f"
  ],
  "since_sha": "2860743961a41f1a6aac34bcbfc4ed70e79fab7f",
  "until_sha": "2860743961a41f1a6aac34bcbfc4ed70e79fab7f",
  "cognitive_friction_score": 0.48000002,
  "ai_attributed": false,
  "attribution_pct": 0.009259259,
  "zombie": false,
  "endorsement_status": "excluded",
  "audited_at": "2026-04-26T21:17:00Z"
}